{"_type":"export","__export_format":4,"__export_date":"2019-10-20T15:47:54.770Z","__export_source":"insomnia.desktop.app:v7.0.1","resources":[{"_id":"req_d4f8da308e7e4275b4cfd4715e54f23d","authentication":{"token":"{{ token  }}","type":"bearer"},"body":{},"created":1571571525490,"description":"","headers":[],"isPrivate":false,"metaSortKey":-1571506542074.25,"method":"GET","modified":1571571540571,"name":"Index","parameters":[],"parentId":"fld_09dbcbe383cb4c35b4967c84d4ef4b31","settingDisableRenderRequestBody":false,"settingEncodeUrl":true,"settingRebuildPath":true,"settingSendCookies":true,"settingStoreCookies":true,"url":"{{ baseUrl  }}/students/1/help-orders","_type":"request"},{"_id":"fld_09dbcbe383cb4c35b4967c84d4ef4b31","created":1571571518374,"description":"","environment":{},"environmentPropertyOrder":null,"metaSortKey":-1571571518374,"modified":1571571518374,"name":"Help Orders","parentId":"wrk_fa84e579324245109b0aa439cc6b7119","_type":"request_group"},{"_id":"wrk_fa84e579324245109b0aa439cc6b7119","created":1571240425625,"description":"","modified":1571240425625,"name":"gym-point","parentId":null,"_type":"workspace"},{"_id":"req_39759ddad34f452b84a6263e62b9b462","authentication":{"token":"{{ token  }}","type":"bearer"},"body":{"mimeType":"application/json","text":"{\n\t\"question\": \"Ola posso treinar mais amanha ?\"\n}"},"created":1571571645613,"description":"","headers":[{"id":"pair_b6ee6481341249d99c7cc65d5626b0d7","name":"Content-Type","value":"application/json"}],"isPrivate":false,"metaSortKey":-1571506542061.75,"method":"POST","modified":1571571701379,"name":"Create","parameters":[],"parentId":"fld_09dbcbe383cb4c35b4967c84d4ef4b31","settingDisableRenderRequestBody":false,"settingEncodeUrl":true,"settingRebuildPath":true,"settingSendCookies":true,"settingStoreCookies":true,"url":"{{ baseUrl  }}/students/1/help-orders","_type":"request"},{"_id":"req_cc89bc4867234a7484b0e162f43a5746","authentication":{"token":"{{ token  }}","type":"bearer"},"body":{"mimeType":"application/json","text":"{\n\t\"answer\": \"Voce pode vir amanha sim\"\n}"},"created":1571571962626,"description":"","headers":[{"id":"pair_b6ee6481341249d99c7cc65d5626b0d7","name":"Content-Type","value":"application/json"}],"isPrivate":false,"metaSortKey":-1571506542055.5,"method":"PUT","modified":1571572046199,"name":"Update","parameters":[],"parentId":"fld_09dbcbe383cb4c35b4967c84d4ef4b31","settingDisableRenderRequestBody":false,"settingEncodeUrl":true,"settingRebuildPath":true,"settingSendCookies":true,"settingStoreCookies":true,"url":"{{ baseUrl  }}/help-orders/1/answer","_type":"request"},{"_id":"req_55fce8394a5545e2b47dec81d0c027a8","authentication":{"token":"{{ token  }}","type":"bearer"},"body":{},"created":1571570347196,"description":"","headers":[],"isPrivate":false,"metaSortKey":-1571506542099.25,"method":"GET","modified":1571570363980,"name":"Index","parameters":[],"parentId":"fld_92fb9e062538424192b5d5f278192929","settingDisableRenderRequestBody":false,"settingEncodeUrl":true,"settingRebuildPath":true,"settingSendCookies":true,"settingStoreCookies":true,"url":"{{ baseUrl  }}/students/1/checkins","_type":"request"},{"_id":"fld_92fb9e062538424192b5d5f278192929","created":1571569961251,"description":"","environment":{},"environmentPropertyOrder":null,"metaSortKey":-1571569961252,"modified":1571569961251,"name":"Checkins","parentId":"wrk_fa84e579324245109b0aa439cc6b7119","_type":"request_group"},{"_id":"req_acf79457733c4335a4555e933eaa3386","authentication":{"token":"{{ token  }}","type":"bearer"},"body":{},"created":1571569972348,"description":"","headers":[],"isPrivate":false,"metaSortKey":-1571506542049.25,"method":"POST","modified":1571570697703,"name":"Create","parameters":[],"parentId":"fld_92fb9e062538424192b5d5f278192929","settingDisableRenderRequestBody":false,"settingEncodeUrl":true,"settingRebuildPath":true,"settingSendCookies":true,"settingStoreCookies":true,"url":"{{ baseUrl  }}/students/1/checkins","_type":"request"},{"_id":"req_cd5f1acde77c4da180f642e4df1bd2e3","authentication":{"token":"{{ token  }}","type":"bearer"},"body":{},"created":1571570616073,"description":"","headers":[],"isPrivate":false,"metaSortKey":-1571506195584.875,"method":"DELETE","modified":1571570818591,"name":"Delete","parameters":[],"parentId":"fld_92fb9e062538424192b5d5f278192929","settingDisableRenderRequestBody":false,"settingEncodeUrl":true,"settingRebuildPath":true,"settingSendCookies":true,"settingStoreCookies":true,"url":"{{ baseUrl  }}/checkins/2","_type":"request"},{"_id":"req_80b394c8d5724f99afec39dd04366a99","authentication":{"token":"{{ token  }}","type":"bearer"},"body":{},"created":1571509741266,"description":"","headers":[],"isPrivate":false,"metaSortKey":-1571510006743,"method":"GET","modified":1571562100085,"name":"Index","parameters":[],"parentId":"fld_f45113a12a81401c9da5bdfca0bb842d","settingDisableRenderRequestBody":false,"settingEncodeUrl":true,"settingRebuildPath":true,"settingSendCookies":true,"settingStoreCookies":true,"url":"{{ baseUrl  }}/enrollments","_type":"request"},{"_id":"fld_f45113a12a81401c9da5bdfca0bb842d","created":1571509734437,"description":"","environment":{},"environmentPropertyOrder":null,"metaSortKey":-1571509734437,"modified":1571509734437,"name":"Enrollments","parentId":"wrk_fa84e579324245109b0aa439cc6b7119","_type":"request_group"},{"_id":"req_d0d47028440c451ca3ce3e09fc103488","authentication":{"token":"{{ token  }}","type":"bearer"},"body":{"mimeType":"application/json","text":"{\n\t\"start_date\":  \"2019-10-20T08:52:43.087Z\",\n\t\"student_id\": 1,\n\t\"plan_id\": 5\n}"},"created":1571510006693,"description":"","headers":[{"id":"pair_c5b5793defcb46af8dadc9d3a9d7ff76","name":"Content-Type","value":"application/json"}],"isPrivate":false,"metaSortKey":-1571510006693,"method":"POST","modified":1571561581685,"name":"Create","parameters":[],"parentId":"fld_f45113a12a81401c9da5bdfca0bb842d","settingDisableRenderRequestBody":false,"settingEncodeUrl":true,"settingRebuildPath":true,"settingSendCookies":true,"settingStoreCookies":true,"url":"{{ baseUrl  }}/enrollments","_type":"request"},{"_id":"req_fe45454cb15b4904bf8a84c3749a0894","authentication":{"token":"{{ token  }}","type":"bearer"},"body":{"mimeType":"application/json","text":"{\n\t\"start_date\":  \"2019-09-20T08:52:43.087Z\",\n\t\"student_id\": 1,\n\t\"plan_id\": 5\n}"},"created":1571562533329,"description":"","headers":[{"id":"pair_c5b5793defcb46af8dadc9d3a9d7ff76","name":"Content-Type","value":"application/json"}],"isPrivate":false,"metaSortKey":-1571507234978,"method":"PUT","modified":1571566467906,"name":"Update","parameters":[],"parentId":"fld_f45113a12a81401c9da5bdfca0bb842d","settingDisableRenderRequestBody":false,"settingEncodeUrl":true,"settingRebuildPath":true,"settingSendCookies":true,"settingStoreCookies":true,"url":"{{ baseUrl  }}/enrollments/6","_type":"request"},{"_id":"req_f0d332b5fd914bbeb0217bc6b3541961","authentication":{"token":"{{ token  }}","type":"bearer"},"body":{},"created":1571564334551,"description":"","headers":[],"isPrivate":false,"metaSortKey":-1571505849120.5,"method":"DELETE","modified":1571568920703,"name":"Delete","parameters":[],"parentId":"fld_f45113a12a81401c9da5bdfca0bb842d","settingDisableRenderRequestBody":false,"settingEncodeUrl":true,"settingRebuildPath":true,"settingSendCookies":true,"settingStoreCookies":true,"url":"{{ baseUrl  }}/enrollments/15","_type":"request"},{"_id":"req_5ccff5f5fe37451c9c3201505976773e","authentication":{"token":"{{ token  }}","type":"bearer"},"body":{},"created":1571504454572,"description":"","headers":[],"isPrivate":false,"metaSortKey":-1571504463263,"method":"GET","modified":1571504489527,"name":"Index","parameters":[],"parentId":"fld_6f2719b87cac4a8a96185b997187b14c","settingDisableRenderRequestBody":false,"settingEncodeUrl":true,"settingRebuildPath":true,"settingSendCookies":true,"settingStoreCookies":true,"url":"{{ baseUrl  }}/plans","_type":"request"},{"_id":"fld_6f2719b87cac4a8a96185b997187b14c","created":1571504442378,"description":"","environment":{},"environmentPropertyOrder":null,"metaSortKey":-1571504442378,"modified":1571504442378,"name":"Plans","parentId":"wrk_fa84e579324245109b0aa439cc6b7119","_type":"request_group"},{"_id":"req_7801ccdc990b437fb033a7d2c7c3f363","authentication":{"token":"{{ token  }}","type":"bearer"},"body":{"mimeType":"application/json","text":"{\n\t\"title\": \"Mega Gold\",\n\t\"duration\": 12,\n\t\"price\": 12.12\n}"},"created":1571504510336,"description":"","headers":[{"id":"pair_3cca5e8b5aa946a59a4768d9d3fba6b8","name":"Content-Type","value":"application/json"}],"isPrivate":false,"metaSortKey":-1571497138053,"method":"POST","modified":1571507617537,"name":"Create","parameters":[],"parentId":"fld_6f2719b87cac4a8a96185b997187b14c","settingDisableRenderRequestBody":false,"settingEncodeUrl":true,"settingRebuildPath":true,"settingSendCookies":true,"settingStoreCookies":true,"url":"{{ baseUrl  }}/plans","_type":"request"},{"_id":"req_fec3ca3fea2e4df6ba924c12cb15d523","authentication":{"token":"{{ token  }}","type":"bearer"},"body":{"mimeType":"application/json","text":"{\n\t\"title\": \"Mega Golds\",\n\t\"duration\": 11,\n\t\"price\": 120.00\n}"},"created":1571504511894,"description":"","headers":[{"id":"pair_1894346b729140e3bfbc9c4ccab3a2a4","name":"Content-Type","value":"application/json"}],"isPrivate":false,"metaSortKey":-1571493475448,"method":"PUT","modified":1571508151652,"name":"Update","parameters":[],"parentId":"fld_6f2719b87cac4a8a96185b997187b14c","settingDisableRenderRequestBody":false,"settingEncodeUrl":true,"settingRebuildPath":true,"settingSendCookies":true,"settingStoreCookies":true,"url":"{{ baseUrl  }}/plans/1","_type":"request"},{"_id":"req_2e97cf6cd3e2417c9ba84727c1834ca5","authentication":{"token":"{{ token  }}","type":"bearer"},"body":{},"created":1571508536646,"description":"","headers":[],"isPrivate":false,"metaSortKey":-1571493475398,"method":"DELETE","modified":1571508702451,"name":"Delete","parameters":[],"parentId":"fld_6f2719b87cac4a8a96185b997187b14c","settingDisableRenderRequestBody":false,"settingEncodeUrl":true,"settingRebuildPath":true,"settingSendCookies":true,"settingStoreCookies":true,"url":"{{ baseUrl  }}/plans/4","_type":"request"},{"_id":"req_31c41ee60cab4df58193540187b81a8d","authentication":{"token":"{{ token  }}","type":"bearer"},"body":{},"created":1571246724871,"description":"","headers":[],"isPrivate":false,"metaSortKey":-1571246724872,"method":"GET","modified":1571561810353,"name":"Index","parameters":[],"parentId":"fld_66ce08d39607402798e2b4b459b945f7","settingDisableRenderRequestBody":false,"settingEncodeUrl":true,"settingRebuildPath":true,"settingSendCookies":true,"settingStoreCookies":true,"url":"{{ baseUrl  }}/students","_type":"request"},{"_id":"fld_66ce08d39607402798e2b4b459b945f7","created":1571241068963,"description":"","environment":{},"environmentPropertyOrder":null,"metaSortKey":-1571241068963,"modified":1571241068963,"name":"Students","parentId":"wrk_fa84e579324245109b0aa439cc6b7119","_type":"request_group"},{"_id":"req_6be42618dc284569bd3528ffe0b59c37","authentication":{"token":"{{ token  }}","type":"bearer"},"body":{"mimeType":"application/json","text":"{\n\t\"name\": \"Isabela Alecio\",\n\t\"email\": \"isabela.alecio6@gmail.com\",\n\t\"peso\": 40,\n\t\"altura\": 1.70\n}"},"created":1571245503221,"description":"","headers":[{"id":"pair_2e6e5fcb47e044d18993aa383ce69576","name":"Content-Type","value":"application/json"}],"isPrivate":false,"metaSortKey":-1571243293896,"method":"POST","modified":1571561820614,"name":"Create","parameters":[],"parentId":"fld_66ce08d39607402798e2b4b459b945f7","settingDisableRenderRequestBody":false,"settingEncodeUrl":true,"settingRebuildPath":true,"settingSendCookies":true,"settingStoreCookies":true,"url":"{{ baseUrl  }}/students","_type":"request"},{"_id":"req_1e63454470454286a0a4ca8b719f3b27","authentication":{"token":"{{ token  }}","type":"bearer"},"body":{"mimeType":"application/json","text":"{\n\t\"name\": \"Alan Fagner\",\n\t\"email\": \"alan.f.goncalves@hotmail.com\",\n\t\"peso\": 100,\n\t\"altura\": 1.89\n}"},"created":1571241084571,"description":"","headers":[{"id":"pair_f3b5dbd8169c4fae967fe572c429177e","name":"Content-Type","value":"application/json"}],"isPrivate":false,"metaSortKey":-1571241084571,"method":"PUT","modified":1571247960755,"name":"Update","parameters":[],"parentId":"fld_66ce08d39607402798e2b4b459b945f7","settingDisableRenderRequestBody":false,"settingEncodeUrl":true,"settingRebuildPath":true,"settingSendCookies":true,"settingStoreCookies":true,"url":"{{ baseUrl  }}/students/10","_type":"request"},{"_id":"req_428afe6715d040939ed21b9a8cb19040","authentication":{},"body":{"mimeType":"application/json","text":"{\n\t\"email\": \"admin@gympoint.com\",\n\t\"password\": \"123456\"\n}"},"created":1571240479016,"description":"","headers":[{"id":"pair_122ba049eb0549ab8e368bd7d234bc7f","name":"Content-Type","value":"application/json"}],"isPrivate":false,"metaSortKey":-1571240479017,"method":"POST","modified":1571241055050,"name":"Create","parameters":[],"parentId":"fld_9817897934fc4fd1b73e85532766179b","settingDisableRenderRequestBody":false,"settingEncodeUrl":true,"settingRebuildPath":true,"settingSendCookies":true,"settingStoreCookies":true,"url":"{{ baseUrl  }}/sessions","_type":"request"},{"_id":"fld_9817897934fc4fd1b73e85532766179b","created":1571240449472,"description":"","environment":{},"environmentPropertyOrder":null,"metaSortKey":-1571240449472,"modified":1571240449472,"name":"Sessions","parentId":"wrk_fa84e579324245109b0aa439cc6b7119","_type":"request_group"},{"_id":"env_86b265e1e0690c72b2e893f8dd51b95176a72f10","color":null,"created":1571240425660,"data":{"baseUrl":"http://localhost:3333","token":"eyJhbGciOiJIUzI1NiIsInR5cCI6IkpXVCJ9.eyJpZCI6MywiYWRtaW4iOnRydWUsImlhdCI6MTU3MTUwNTE2NSwiZXhwIjoxNTcyMTA5OTY1fQ.D8Rb_W4wOb5uzdLVVDsq8uLOQoMuC88YqxqcTU5bZOg"},"dataPropertyOrder":{"&":["baseUrl","token"]},"isPrivate":false,"metaSortKey":1571240425660,"modified":1571505177147,"name":"Base Environment","parentId":"wrk_fa84e579324245109b0aa439cc6b7119","_type":"environment"},{"_id":"jar_86b265e1e0690c72b2e893f8dd51b95176a72f10","cookies":[],"created":1571240425663,"modified":1571240425663,"name":"Default Jar","parentId":"wrk_fa84e579324245109b0aa439cc6b7119","_type":"cookie_jar"}]}